{"diff_netsenders_30": 0, "diff_netsenders_365": -2, "diff_netsenders_7": -3, "diff_netsent_30": -21, "diff_netsent_365": -7, "diff_netsent_7": -9, "first_date": "2010-01-06", "last_date": "2015-11-26", "percentage_senders_30": 0, "percentage_senders_365": 28, "percentage_senders_7": 100, "percentage_sent_30": 38, "percentage_sent_365": 1, "percentage_sent_7": 100, "repositories": 14, "senders": 10, "senders_30": 5, "senders_365": 5, "senders_7": 0, "senders_init": 9, "senders_response": 10, "sent": 3467, "sent_30": 33, "sent_365": 554, "sent_7": 0, "sent_response": 3150, "threads": 317}