{"actions": [18356, 5765, 838], "added_lines": [663217.0, 416376.0, 172951.0], "added_lines_30": [11575.0, 10473.0, 0], "added_lines_365": [300841.0, 223097.0, 0], "added_lines_7": [3701.0, 2336.0, 0], "authors": [46, 15, 2], "authors_30": [8, 3, 0], "authors_365": [29, 13, 0], "authors_7": [3, 2, 0], "avg_commits_author": [46.83, 21.53, 5.0], "avg_commits_month": [71.8, 17.0, 1.43], "avg_files_author": [218.93, 200.13, 253.0], "avg_files_month": [335.7, 158.0, 72.29], "branches": [273, 10, 1], "commits": [2154, 323, 10], "commits_30": [50, 47, 0], "commits_365": [722, 245, 0], "commits_7": [24, 12, 0], "committers": [46, 15, 2], "diff_netadded_lines_30": [-3107.0, -4653.0, 0], "diff_netadded_lines_365": [-25749.0, 29818.0, -156314.0], "diff_netadded_lines_7": [-563.0, -3279.0, 0], "diff_netauthors_30": [-1, -1, 0], "diff_netauthors_365": [3, 7, -2], "diff_netauthors_7": [0, -1, 0], "diff_netcommits_30": [-36, 23, 0], "diff_netcommits_365": [-594, 167, -9], "diff_netcommits_7": [17, -4, 0], "diff_netfiles_30": [-158, 202, 0], "diff_netfiles_365": [-490, 864, -493], "diff_netfiles_7": [46, 43, 0], "diff_netnewauthors_30": [0, 0, 0], "diff_netnewauthors_365": [-8, 3, -1], "diff_netnewauthors_7": [0, 0, 0], "diff_netremoved_lines_30": [358.0, -689.0, 0], "diff_netremoved_lines_365": [63176.0, 28828.0, -19497.0], "diff_netremoved_lines_7": [-714.0, -512.0, 0], "files": [10071, 3002, 506], "files_30": [270, 403, 0], "files_365": [4604, 2141, 0], "files_7": [99, 217, 0], "first_date": ["2013-09-30", "2014-08-22", "2014-04-08"], "last_date": ["2016-04-08", "2016-04-07", "2014-12-04"], "name": ["geomesa.git", "geogig.git", "org.locationtech.geoff"], "newauthors": [46, 15, 2], "newauthors_30": [1, 0, 0], "newauthors_365": [14, 9, 0], "newauthors_7": [0, 0, 0], "percentage_added_lines_30": [21, 30, 0], "percentage_added_lines_365": [7, 15, 100], "percentage_added_lines_7": [13, 58, 0], "percentage_authors_30": [11, 25, 0], "percentage_authors_365": [11, 116, 100], "percentage_authors_7": [0, 33, 0], "percentage_commits_30": [41, 95, 0], "percentage_commits_365": [45, 214, 100], "percentage_commits_7": [242, 25, 0], "percentage_files_30": [36, 100, 0], "percentage_files_365": [9, 67, 100], "percentage_files_7": [86, 24, 0], "percentage_newauthors_30": [0, 0, 0], "percentage_newauthors_365": [36, 50, 100], "percentage_newauthors_7": [0, 0, 0], "percentage_removed_lines_30": [6, 15, 0], "percentage_removed_lines_365": [39, 110, 100], "percentage_removed_lines_7": [28, 29, 0], "removed_lines": [386495.0, 81140.0, 19497.0], "removed_lines_30": [5918.0, 3626.0, 0], "removed_lines_365": [222112.0, 54984.0, 0], "removed_lines_7": [1825.0, 1196.0, 0], "repositories": [1, 1, 1]}