{"diff_netsenders_30": -6, "diff_netsenders_365": -23, "diff_netsenders_7": 0, "diff_netsent_30": -17, "diff_netsent_365": -103, "diff_netsent_7": 0, "first_date": "2002-12-18", "last_date": "2016-03-25", "percentage_senders_30": 66, "percentage_senders_365": 39, "percentage_senders_7": 0, "percentage_sent_30": 85, "percentage_sent_365": 31, "percentage_sent_7": 0, "repositories": 1, "senders": 1785, "senders_30": 3, "senders_365": 35, "senders_7": 1, "senders_init": 1605, "senders_response": 1024, "sent": 14961, "sent_30": 3, "sent_365": 223, "sent_7": 1, "sent_response": 9602, "threads": 5359}