{"diff_netsenders_30": -3, "diff_netsenders_365": -4, "diff_netsenders_7": 3, "diff_netsent_30": -10, "diff_netsent_365": -16, "diff_netsent_7": 11, "first_date": "2001-11-01", "last_date": "2014-10-12", "percentage_senders_30": 33, "percentage_senders_365": 14, "percentage_senders_7": 300, "percentage_sent_30": 31, "percentage_sent_365": 3, "percentage_sent_7": 1100, "repositories": 1, "senders": 67, "senders_30": 6, "senders_365": 23, "senders_7": 4, "senders_init": 55, "senders_response": 54, "sent": 4080, "sent_30": 22, "sent_365": 445, "sent_7": 12, "sent_response": 3286, "threads": 794}