{"changed": 22863, "changers": 2300, "closed": 21591, "closed_30": 5, "closed_365": 39, "closed_7": 0, "closers": 464, "closers_30": 2, "closers_365": 11, "closers_7": 0, "diff_netclosed_30": -4, "diff_netclosed_365": -272, "diff_netclosed_7": -3, "diff_netclosers_30": 0, "diff_netclosers_365": -18, "diff_netclosers_7": -2, "opened": 23037, "openers": 2900, "percentage_closed_30": 44, "percentage_closed_365": 87, "percentage_closed_7": 100, "percentage_closers_30": 0, "percentage_closers_365": 62, "percentage_closers_7": 100, "trackers": 1}