{"changed": 1188, "changers": 34, "closed": 439, "closed_30": 3, "closed_365": 33, "closed_7": 0, "closers": 5, "closers_30": 1, "closers_365": 2, "closers_7": 0, "diff_netclosed_30": 2, "diff_netclosed_365": -179, "diff_netclosed_7": 0, "diff_netclosers_30": 0, "diff_netclosers_365": 0, "diff_netclosers_7": 0, "opened": 426, "openers": 33, "percentage_closed_30": 200, "percentage_closed_365": 84, "percentage_closed_7": 0, "percentage_closers_30": 0, "percentage_closers_365": 0, "percentage_closers_7": 0, "trackers": 33}