{"authors": 19, "authors_30": 11, "authors_365": 19, "authors_7": 3, "avg_commits_author": 12.82, "avg_commits_month": 24.22, "commits": 218, "commits_30": 44, "commits_365": 218, "commits_7": 6, "committers": 19, "diff_netauthors_30": 3, "diff_netauthors_365": 19, "diff_netauthors_7": -2, "diff_netcommits_30": -49, "diff_netcommits_365": 218, "diff_netcommits_7": 0, "files": 218, "first_date": "2015-07-17", "last_date": "2016-04-21", "percentage_authors_30": 37, "percentage_authors_365": 0, "percentage_authors_7": 40, "percentage_commits_30": 52, "percentage_commits_365": 0, "percentage_commits_7": 0, "repositories": 4}