{"changed": 73671, "changers": 7193, "closed": 66835, "closed_30": 115, "closed_365": 1397, "closed_7": 17, "closers": 1217, "closers_30": 15, "closers_365": 79, "closers_7": 7, "diff_netclosed_30": -11, "diff_netclosed_365": -103, "diff_netclosed_7": -10, "diff_netclosers_30": -2, "diff_netclosers_365": -4, "diff_netclosers_7": 0, "opened": 74460, "openers": 9916, "percentage_closed_30": 8, "percentage_closed_365": 6, "percentage_closed_7": 37, "percentage_closers_30": 11, "percentage_closers_365": 4, "percentage_closers_7": 0, "trackers": 2}