{"added_lines": 1087164.0, "authors": 161, "authors_30": 4, "authors_365": 26, "authors_7": 0, "avg_commits_author": 166.39, "avg_commits_month": 169.54, "commits": 26788, "commits_30": 5, "commits_365": 146, "commits_7": 0, "committers": 161, "diff_netauthors_30": 1, "diff_netauthors_365": 4, "diff_netauthors_7": -3, "diff_netcommits_30": 0, "diff_netcommits_365": -27, "diff_netcommits_7": -3, "files": 199233, "first_date": "2001-05-02", "last_date": "2015-01-16", "percentage_authors_30": 33, "percentage_authors_365": 18, "percentage_authors_7": 100, "percentage_commits_30": 0, "percentage_commits_365": 15, "percentage_commits_7": 100, "removed_lines": 733075.0, "repositories": 1}