{"closers.": {"closed": [709, 386, 270, 138, 99, 67, 63, 31, 26, 21], "closers": ["Marc Khouzam", "Marc-Andre Laperle", "unknown", "aleon", "Jacques Bouthillier", "Bernd Hufmann", "vrubezhny", "Marc Dumais", "Alexandre Montplaisir", "Matthew Khouzam"], "id": [30, 540, 438, 679, 683, 2441, 616, 2846, 2451, 2452]}, "closers.last month": {"closed": [709, 386, 270, 138, 99, 67, 63, 31, 26, 21], "closers": ["Marc Khouzam", "Marc-Andre Laperle", "unknown", "aleon", "Jacques Bouthillier", "Bernd Hufmann", "vrubezhny", "Marc Dumais", "Alexandre Montplaisir", "Matthew Khouzam"], "id": [30, 540, 438, 679, 683, 2441, 616, 2846, 2451, 2452]}, "closers.last year": {"closed": [709, 386, 270, 138, 99, 67, 63, 31, 26, 21], "closers": ["Marc Khouzam", "Marc-Andre Laperle", "unknown", "aleon", "Jacques Bouthillier", "Bernd Hufmann", "vrubezhny", "Marc Dumais", "Alexandre Montplaisir", "Matthew Khouzam"], "id": [30, 540, 438, 679, 683, 2441, 616, 2846, 2451, 2452]}}