{"abandoned": 442, "abandoned_30": 3, "abandoned_365": 190, "abandoned_7": 0, "closed": 3728, "closed_30": 28, "closed_365": 1674, "closed_7": 4, "diff_netabandoned_30": 0, "diff_netabandoned_365": 7, "diff_netabandoned_7": 0, "diff_netclosed_30": -76, "diff_netclosed_365": 147, "diff_netclosed_7": 3, "diff_netmerged_30": -76, "diff_netmerged_365": 140, "diff_netmerged_7": 3, "diff_netpending_30": -14, "diff_netpending_365": 26, "diff_netpending_7": 2, "diff_netsubmitted_30": -90, "diff_netsubmitted_365": 173, "diff_netsubmitted_7": 5, "diff_netsubmitters_30": -3, "diff_netsubmitters_365": 6, "diff_netsubmitters_7": 2, "first_date": "2012-02-10", "inprogress": 0, "last_date": "2014-11-05", "merged": 3286, "merged_30": 25, "merged_365": 1484, "merged_7": 4, "new": 67, "opened": 67, "pending": 67, "pending_30": 4, "pending_365": 66, "pending_7": 3, "percentage_abandoned_30": 0, "percentage_abandoned_365": 3, "percentage_abandoned_7": 0, "percentage_closed_30": 73, "percentage_closed_365": 9, "percentage_closed_7": 300, "percentage_merged_30": 75, "percentage_merged_365": 10, "percentage_merged_7": 300, "percentage_pending_30": 77, "percentage_pending_365": 65, "percentage_pending_7": 200, "percentage_submitted_30": 73, "percentage_submitted_365": 11, "percentage_submitted_7": 250, "percentage_submitters_30": 23, "percentage_submitters_365": 19, "percentage_submitters_7": 100, "review_time_days_avg": "NA", "review_time_days_median": "NA", "reviewers": 58, "submitted": 3795, "submitted_30": 32, "submitted_365": 1740, "submitted_7": 7, "submitters": 50, "submitters_30": 10, "submitters_365": 37, "submitters_7": 4}