{"abandoned": 214, "abandoned_30": 5, "abandoned_365": 103, "abandoned_7": 3, "active_core_reviewers": 8, "active_core_reviewers_30": 6, "active_core_reviewers_365": 8, "active_core_reviewers_7": 4, "closed": 497, "closed_30": 36, "closed_365": 336, "closed_7": 19, "diff_netabandoned_30": -2, "diff_netabandoned_365": 41, "diff_netabandoned_7": 2, "diff_netactive_core_reviewers_30": 2, "diff_netactive_core_reviewers_365": 5, "diff_netactive_core_reviewers_7": 3, "diff_netclosed_30": 7, "diff_netclosed_365": 241, "diff_netclosed_7": 14, "diff_netmerged_30": 9, "diff_netmerged_365": 200, "diff_netmerged_7": 12, "diff_netparticipants_30": -6, "diff_netparticipants_365": 13, "diff_netparticipants_7": 1, "diff_netpatchset_submitters_30": -4, "diff_netpatchset_submitters_365": 4, "diff_netpatchset_submitters_7": 4, "diff_netpending_30": 10, "diff_netpending_365": 24, "diff_netpending_7": -4, "diff_netreviewers_30": 0, "diff_netreviewers_365": 5, "diff_netreviewers_7": 3, "diff_netsent_patchsets_30": 57, "diff_netsent_patchsets_365": 922, "diff_netsent_patchsets_7": 34, "diff_netsubmitted_30": 17, "diff_netsubmitted_365": 265, "diff_netsubmitted_7": 10, "diff_netsubmitters_30": 1, "diff_netsubmitters_365": 6, "diff_netsubmitters_7": 2, "diff_netvoted_patchsets_30": 12, "diff_netvoted_patchsets_365": 218, "diff_netvoted_patchsets_7": 13, "first_date": "2012-10-02", "inprogress": 0, "last_date": "2016-01-11", "merged": 283, "merged_30": 31, "merged_365": 233, "merged_7": 16, "new": 58, "opened": 58, "participants": 56, "participants_30": 13, "participants_365": 41, "participants_7": 9, "patchset_submitters": 44, "patchset_submitters_30": 10, "patchset_submitters_365": 27, "patchset_submitters_7": 8, "pending": 58, "pending_30": 19, "pending_365": 50, "pending_7": 7, "percentage_abandoned_30": 28, "percentage_abandoned_365": 66, "percentage_abandoned_7": 200, "percentage_active_core_reviewers_30": 50, "percentage_active_core_reviewers_365": 166, "percentage_active_core_reviewers_7": 300, "percentage_closed_30": 24, "percentage_closed_365": 253, "percentage_closed_7": 280, "percentage_merged_30": 40, "percentage_merged_365": 606, "percentage_merged_7": 300, "percentage_participants_30": 31, "percentage_participants_365": 46, "percentage_participants_7": 12, "percentage_patchset_submitters_30": 28, "percentage_patchset_submitters_365": 17, "percentage_patchset_submitters_7": 100, "percentage_pending_30": 111, "percentage_pending_365": 92, "percentage_pending_7": 36, "percentage_reviewers_30": 0, "percentage_reviewers_365": 50, "percentage_reviewers_7": 150, "percentage_sent_patchsets_30": 40, "percentage_sent_patchsets_365": 278, "percentage_sent_patchsets_7": 73, "percentage_submitted_30": 44, "percentage_submitted_365": 219, "percentage_submitted_7": 62, "percentage_submitters_30": 12, "percentage_submitters_365": 30, "percentage_submitters_7": 50, "percentage_voted_patchsets_30": 40, "percentage_voted_patchsets_365": 357, "percentage_voted_patchsets_7": 260, "review_time_days_avg": 33.66, "review_time_days_median": 11.5, "reviewers": 19, "reviewers_30": 7, "reviewers_365": 15, "reviewers_7": 5, "sent_patchsets": 1678, "sent_patchsets_30": 197, "sent_patchsets_365": 1253, "sent_patchsets_7": 80, "submitted": 555, "submitted_30": 55, "submitted_365": 386, "submitted_7": 26, "submitters": 45, "submitters_30": 9, "submitters_365": 26, "submitters_7": 6, "voted_patchsets": 373, "voted_patchsets_30": 42, "voted_patchsets_365": 279, "voted_patchsets_7": 18}