{"changed": 879, "changers": 383, "closed": 664, "closed_30": 1, "closed_365": 46, "closed_7": 0, "closers": 67, "closers_30": 1, "closers_365": 16, "closers_7": 0, "diff_netclosed_30": -3, "diff_netclosed_365": -57, "diff_netclosed_7": 0, "diff_netclosers_30": -3, "diff_netclosers_365": 3, "diff_netclosers_7": 0, "opened": 1026, "openers": 391, "percentage_closed_30": 75, "percentage_closed_365": 55, "percentage_closed_7": 0, "percentage_closers_30": 75, "percentage_closers_365": 23, "percentage_closers_7": 0, "trackers": 1}