{"closers.": {"closed": [104, 40, 4, 4, 2, 2, 2, 1, 1], "closers": ["goulwen.lefur@obeo.fr", "Stephane Bouchet", "Nathalie Lepine", "thalesepm", "Jean Barata", "milesparker@gmail.com", "Patrick Tessier", "Esteban Dugueperoux", "gonzague.reydet@gmail.com"], "id": [65412, 3976, 3089, 329285, 9473, 64768, 1320, 2639, 4005]}, "closers.last month": {"closed": [], "closers": [], "id": []}, "closers.last year": {"closed": [2, 1], "closers": ["goulwen.lefur@obeo.fr", "Esteban Dugueperoux"], "id": [65412, 2639]}}