{"bmitickets": 94.34, "changed": 556, "changers": 83, "closed": 533, "closed_30": 3, "closed_365": 72, "closed_7": 0, "closers": 13, "closers_30": 1, "closers_365": 7, "closers_7": 0, "diff_netclosed_30": 1, "diff_netclosed_365": 25, "diff_netclosed_7": -1, "diff_netclosers_30": 0, "diff_netclosers_365": 2, "diff_netclosers_7": 0, "first_date": "2006-09-13", "last_date": "2015-02-04", "opened": 565, "openers": 107, "percentage_closed_30": 50, "percentage_closed_365": 53, "percentage_closed_7": 100, "percentage_closers_30": 0, "percentage_closers_365": 40, "percentage_closers_7": 0, "trackers": 1}