{"changed": 1120, "changers": 601, "closed": 911, "closed_30": 52, "closed_365": 244, "closed_7": 8, "closers": 112, "closers_30": 10, "closers_365": 34, "closers_7": 3, "diff_netclosed_30": 39, "diff_netclosed_365": 175, "diff_netclosed_7": 5, "diff_netclosers_30": 7, "diff_netclosers_365": 13, "diff_netclosers_7": 2, "opened": 1171, "openers": 380, "percentage_closed_30": 300, "percentage_closed_365": 253, "percentage_closed_7": 166, "percentage_closers_30": 233, "percentage_closers_365": 61, "percentage_closers_7": 200, "trackers": 1}