{"closers.": {"closed": [116, 90, 26, 11, 6, 5, 2, 2, 1, 1], "closers": ["Pierre-Charles David", "Maxime PORHEL", "Laurent Redor", "Esteban Dugueperoux", "alagarde", "Florian Barbin", "Cedric Brun", "Steve Monnier", "diogo vicente", "Ed.Willink"], "id": [298321, 880, 2057, 2639, 2635, 2638, 554, 2640, 53938, 219]}, "closers.last month": {"closed": [14, 9, 2, 1, 1, 1], "closers": ["Maxime PORHEL", "Laurent Redor", "Pierre-Charles David", "Cedric Brun", "Esteban Dugueperoux", "Steve Monnier"], "id": [880, 2057, 298321, 554, 2639, 2640]}, "closers.last year": {"closed": [116, 90, 26, 11, 6, 5, 2, 2, 1, 1], "closers": ["Pierre-Charles David", "Maxime PORHEL", "Laurent Redor", "Esteban Dugueperoux", "alagarde", "Florian Barbin", "Cedric Brun", "Steve Monnier", "diogo vicente", "Ed.Willink"], "id": [298321, 880, 2057, 2639, 2635, 2638, 554, 2640, 53938, 219]}}