{"authors": 20, "authors_30": 6, "authors_365": 17, "authors_7": 1, "avg_commits_author": 95.85, "avg_commits_month": 29.95, "commits": 1917, "commits_30": 34, "commits_365": 435, "commits_7": 6, "committers": 20, "diff_netauthors_30": -2, "diff_netauthors_365": 10, "diff_netauthors_7": -2, "diff_netcommits_30": 5, "diff_netcommits_365": 75, "diff_netcommits_7": 1, "files": 16296, "first_date": "2010-11-25", "last_date": "2016-03-29", "percentage_authors_30": 25, "percentage_authors_365": 142, "percentage_authors_7": 66, "percentage_commits_30": 17, "percentage_commits_365": 20, "percentage_commits_7": 20, "repositories": 1}