{"authors": 189, "authors_30": 13, "authors_365": 52, "authors_7": 2, "avg_commits_author": 151.72, "avg_commits_month": 173.79, "commits": 28676, "commits_30": 80, "commits_365": 951, "commits_7": 3, "committers": 189, "diff_netauthors_30": -2, "diff_netauthors_365": -9, "diff_netauthors_7": -3, "diff_netcommits_30": -28, "diff_netcommits_365": -126, "diff_netcommits_7": -6, "files": 66809, "first_date": "2002-06-26", "last_date": "2016-04-08", "percentage_authors_30": 13, "percentage_authors_365": 14, "percentage_authors_7": 60, "percentage_commits_30": 25, "percentage_commits_365": 11, "percentage_commits_7": 66, "repositories": 1}