{"closers.": {"closed": [917, 436, 355, 65, 3, 2, 2, 1, 1, 1], "closers": ["Konstantin Komissarchik", "Ling Hao", "Shenxue Zhou", "konstantin.komissarchik", "rcernich@sybase.com", "Greg Amerson", "kamesh.sampath@hotmail.com", "Denis Roy", "himanshu161088@hotmail.com", "marcelop"], "id": [1082, 2694, 1079, 432611, 384619, 2262, 378418, 1033, 385964, 309]}, "closers.last month": {"closed": 1, "closers": "Shenxue Zhou", "id": 1079}, "closers.last year": {"closed": [65, 46, 25], "closers": ["konstantin.komissarchik", "Shenxue Zhou", "Konstantin Komissarchik"], "id": [432611, 1079, 1082]}}