{"authors": 27, "authors_30": 1, "authors_365": 4, "authors_7": 1, "avg_commits_author": 386.48, "avg_commits_month": 86.96, "commits": 10435, "commits_30": 8, "commits_365": 321, "commits_7": 1, "committers": 27, "diff_netauthors_30": 0, "diff_netauthors_365": -4, "diff_netauthors_7": 0, "diff_netcommits_30": -16, "diff_netcommits_365": 117, "diff_netcommits_7": -2, "files": 134287, "first_date": "2006-04-01", "last_date": "2016-04-12", "percentage_authors_30": 0, "percentage_authors_365": 50, "percentage_authors_7": 0, "percentage_commits_30": 66, "percentage_commits_365": 57, "percentage_commits_7": 66, "repositories": 1}