{"closers.": {"closed": [549, 364, 291, 179, 131, 41, 24, 15, 9, 6], "closers": ["Chris Jaun", "Nitin Dahyabhai", "mrennie", "berkland@us.ibm.com", "childsb@us.ibm.com", "Carl Anderson", "itewksbu@us.ibm.com", "david_williams@us.ibm.com", "lbustelo@us.ibm.com", "cdeadmin@us.ibm.com"], "id": [612, 611, 610, 381246, 379552, 462, 381449, 273, 380964, 380915]}, "closers.last month": {"closed": [], "closers": [], "id": []}, "closers.last year": {"closed": [5, 2, 1, 1], "closers": ["Chris Jaun", "Nitin Dahyabhai", "Carl Anderson", "Christian Pontesegger"], "id": [612, 611, 462, 813]}}