{"authors": 483, "authors_30": 46, "authors_365": 123, "authors_7": 25, "avg_commits_author": 727.35, "avg_commits_month": 2091.14, "commits": 345198, "commits_30": 657, "commits_365": 10137, "commits_7": 114, "committers": 403, "diff_netauthors_30": -3, "diff_netauthors_365": -30, "diff_netauthors_7": -5, "diff_netcommits_30": -67, "diff_netcommits_365": -3542, "diff_netcommits_7": -35, "first_date": "2001-05-02", "last_date": "2015-05-30", "percentage_authors_30": 6, "percentage_authors_365": 19, "percentage_authors_7": 16, "percentage_commits_30": 9, "percentage_commits_365": 25, "percentage_commits_7": 23, "repositories": 241}