{"added_lines": 6416360.0, "authors": 16, "authors_30": 8, "authors_365": 11, "authors_7": 6, "avg_commits_author": 1116.19, "avg_commits_month": 151.35, "commits": 17859, "commits_30": 175, "commits_365": 2406, "commits_7": 30, "committers": 16, "diff_netauthors_30": 0, "diff_netauthors_365": 0, "diff_netauthors_7": 0, "diff_netcommits_30": 4, "diff_netcommits_365": -2196, "diff_netcommits_7": -22, "files": 59752, "first_date": "2001-05-02", "last_date": "2014-12-25", "percentage_authors_30": 0, "percentage_authors_365": 0, "percentage_authors_7": 0, "percentage_commits_30": 2, "percentage_commits_365": 47, "percentage_commits_7": 42, "removed_lines": 4491580.0, "repositories": 58}