{"added_lines": 339938.0, "authors": 14, "authors_30": 7, "authors_365": 16, "authors_7": 5, "avg_commits_author": 42.43, "avg_commits_month": 54.0, "commits": 594, "commits_30": 74, "commits_365": 595, "commits_7": 22, "committers": 14, "diff_netauthors_30": -3, "diff_netauthors_365": 16, "diff_netauthors_7": 1, "diff_netcommits_30": -30, "diff_netcommits_365": 595, "diff_netcommits_7": 9, "files": 3151, "first_date": "2001-05-02", "last_date": "2014-12-12", "percentage_authors_30": 30, "percentage_authors_365": 0, "percentage_authors_7": 25, "percentage_commits_30": 28, "percentage_commits_365": 0, "percentage_commits_7": 69, "removed_lines": 133787.0, "repositories": 1}