{"allhistory_participants": 77805, "bmitickets": 84.7, "changed": 498130, "changers": 42492, "closed": 433751, "closed_30": 1901, "closed_365": 22813, "closed_7": 370, "closers": 8144, "closers_30": 231, "closers_365": 855, "closers_7": 104, "diff_netclosed_30": 403, "diff_netclosed_365": -1072, "diff_netclosed_7": -60, "diff_netclosers_30": -6, "diff_netclosers_365": -390, "diff_netclosers_7": -14, "first_date": "2001-10-10", "last_date": "2016-03-15", "opened": 512074, "openers": 52551, "organizations": 1, "percentage_closed_30": 26, "percentage_closed_365": 4, "percentage_closed_7": 13, "percentage_closers_30": 2, "percentage_closers_365": 31, "percentage_closers_7": 11, "trackers": 230, "type": "bugzilla", "url": "https://bugs.eclipse.org/bugs/buglist.cgi?product=Mylyn%2520Tasks"}