{"allhistory_participants": 62702, "bmitickets": 85.28, "changed": 467266, "changers": 34483, "closed": 408707, "closed_30": 1460, "closed_365": 19229, "closed_7": 395, "closers": 7134, "closers_30": 212, "closers_365": 967, "closers_7": 111, "companies": 80, "diff_netclosed_30": -432, "diff_netclosed_365": -5064, "diff_netclosed_7": 25, "diff_netclosers_30": 5, "diff_netclosers_365": 33, "diff_netclosers_7": 6, "first_date": "2001-10-10", "last_date": "2015-04-27", "opened": 479259, "openers": 43684, "percentage_closed_30": 22, "percentage_closed_365": 20, "percentage_closed_7": 6, "percentage_closers_30": 2, "percentage_closers_365": 3, "percentage_closers_7": 5, "trackers": 216, "type": "bugzilla", "url": "https://bugs.eclipse.org/bugs/buglist.cgi?product=Mylyn%2520Tasks"}