{"added_lines": 53060195.0, "authors": 61, "authors_30": 18, "authors_365": 41, "authors_7": 10, "avg_commits_author": 260.37, "avg_commits_month": 226.41, "commits": 15622, "commits_30": 200, "commits_365": 2710, "commits_7": 44, "committers": 61, "diff_netauthors_30": 1, "diff_netauthors_365": 20, "diff_netauthors_7": -1, "diff_netcommits_30": -3, "diff_netcommits_365": -45, "diff_netcommits_7": -11, "files": 219240, "first_date": "2001-05-02", "last_date": "2014-11-04", "percentage_authors_30": 5, "percentage_authors_365": 95, "percentage_authors_7": 9, "percentage_commits_30": 1, "percentage_commits_365": 1, "percentage_commits_7": 19, "removed_lines": 39024909.0, "repositories": 1}