{"authors": 4, "authors_30": 2, "authors_365": 4, "authors_7": 0, "avg_commits_author": 53.5, "avg_commits_month": 6.11, "commits": 214, "commits_30": 7, "commits_365": 111, "commits_7": 0, "committers": 4, "diff_netauthors_30": 0, "diff_netauthors_365": 2, "diff_netauthors_7": -1, "diff_netcommits_30": 5, "diff_netcommits_365": 62, "diff_netcommits_7": -2, "first_date": "2012-07-02", "last_date": "2015-06-08", "percentage_authors_30": 0, "percentage_authors_365": 100, "percentage_authors_7": 100, "percentage_commits_30": 250, "percentage_commits_365": 126, "percentage_commits_7": 100, "repositories": 2}