{"authors": 29, "authors_30": 0, "authors_365": 4, "authors_7": 0, "avg_commits_author": 332.03, "avg_commits_month": 77.65, "commits": 9629, "commits_30": 0, "commits_365": 33, "commits_7": 0, "committers": 29, "diff_netauthors_30": 0, "diff_netauthors_365": -2, "diff_netauthors_7": 0, "diff_netcommits_30": 0, "diff_netcommits_365": -31, "diff_netcommits_7": 0, "files": 19283, "first_date": "2005-08-03", "last_date": "2015-12-10", "percentage_authors_30": 0, "percentage_authors_365": 33, "percentage_authors_7": 0, "percentage_commits_30": 0, "percentage_commits_365": 48, "percentage_commits_7": 0, "repositories": 1}