{"bmitickets": 80.99, "changed": 1146, "changers": 96, "closed": 1010, "closed_30": 27, "closed_365": 115, "closed_7": 14, "closers": 28, "closers_30": 1, "closers_365": 7, "closers_7": 1, "diff_netclosed_30": 19, "diff_netclosed_365": -53, "diff_netclosed_7": 11, "diff_netclosers_30": -1, "diff_netclosers_365": -2, "diff_netclosers_7": 1, "first_date": "2007-04-10", "last_date": "2015-03-10", "opened": 1247, "openers": 157, "percentage_closed_30": 237, "percentage_closed_365": 31, "percentage_closed_7": 366, "percentage_closers_30": 50, "percentage_closers_365": 22, "percentage_closers_7": 0, "trackers": 4}