{"authors": 82, "authors_30": 9, "authors_365": 29, "authors_7": 2, "avg_commits_author": 389.3, "avg_commits_month": 238.23, "commits": 31923, "commits_30": 59, "commits_365": 789, "commits_7": 10, "committers": 82, "diff_netauthors_30": 2, "diff_netauthors_365": -2, "diff_netauthors_7": -3, "diff_netcommits_30": -20, "diff_netcommits_365": -868, "diff_netcommits_7": -5, "first_date": "2004-03-06", "last_date": "2015-05-17", "percentage_authors_30": 28, "percentage_authors_365": 6, "percentage_authors_7": 60, "percentage_commits_30": 25, "percentage_commits_365": 52, "percentage_commits_7": 33, "repositories": 12}