{"changed": 13075, "changers": 1823, "closed": 11315, "closed_30": 17, "closed_365": 290, "closed_7": 0, "closers": 339, "closers_30": 4, "closers_365": 24, "closers_7": 0, "diff_netclosed_30": -8, "diff_netclosed_365": -4, "diff_netclosed_7": -4, "diff_netclosers_30": 0, "diff_netclosers_365": -11, "diff_netclosers_7": -1, "opened": 13272, "openers": 1823, "percentage_closed_30": 31, "percentage_closed_365": 1, "percentage_closed_7": 100, "percentage_closers_30": 0, "percentage_closers_365": 31, "percentage_closers_7": 100, "trackers": 13}