{"changed": 18127, "changers": 53, "closed": 10893, "closed_30": 21, "closed_365": 524, "closed_7": 5, "closers": 51, "closers_30": 4, "closers_365": 29, "closers_7": 2, "diff_netclosed_30": -10, "diff_netclosed_365": -797, "diff_netclosed_7": -5, "diff_netclosers_30": -9, "diff_netclosers_365": -5, "diff_netclosers_7": 0, "first_date": "2001-12-12", "last_date": "2014-09-15", "opened": 7735, "openers": 52, "percentage_closed_30": 32, "percentage_closed_365": 60, "percentage_closed_7": 50, "percentage_closers_30": 69, "percentage_closers_365": 14, "percentage_closers_7": 0, "trackers": 49}