{"authors": 38, "authors_30": 4, "authors_365": 10, "authors_7": 0, "avg_commits_author": 243.92, "avg_commits_month": 74.15, "commits": 9269, "commits_30": 12, "commits_365": 91, "commits_7": 0, "committers": 38, "diff_netauthors_30": 2, "diff_netauthors_365": -2, "diff_netauthors_7": -2, "diff_netcommits_30": 10, "diff_netcommits_365": -37, "diff_netcommits_7": -4, "files": 12946, "first_date": "2005-06-17", "last_date": "2015-11-27", "percentage_authors_30": 100, "percentage_authors_365": 16, "percentage_authors_7": 100, "percentage_commits_30": 500, "percentage_commits_365": 28, "percentage_commits_7": 100, "repositories": 1}