{"authors.": {"authors": ["Monika Funke", "Vrishali Doke", "Hichem Talbi", "Sven Rottstock", "Stephan Born", "Simone", "Melek Zribi", "Caroline Rieseler", "Marc Gille", "Roland Stamm"], "commits": [1858, 523, 147, 59, 26, 23, 20, 9, 5, 4], "id": [565, 3116, 2683, 403, 401, 406, 2551, 568, 931, 567]}, "authors.last month": {"authors": ["Monika Funke", "Vrishali Doke", "Hichem Talbi"], "commits": [32, 19, 1], "id": [565, 3116, 2683]}, "authors.last year": {"authors": ["Monika Funke", "Vrishali Doke", "Hichem Talbi", "Melek Zribi", "Stephan Born", "Sven Rottstock", "Simone", "Caroline Rieseler", "Sabri Bousselmi", "Robert Sauer"], "commits": [547, 108, 104, 20, 13, 12, 10, 8, 3, 2], "id": [565, 3116, 2683, 2551, 401, 403, 406, 568, 2553, 400]}}