{"added_lines": 431502.0, "authors": 16, "authors_30": 3, "authors_365": 11, "authors_7": 0, "avg_commits_author": 166.81, "avg_commits_month": 74.14, "commits": 2669, "commits_30": 52, "commits_365": 775, "commits_7": 0, "committers": 16, "diff_netauthors_30": -2, "diff_netauthors_365": 0, "diff_netauthors_7": -2, "diff_netcommits_30": -3, "diff_netcommits_365": -75, "diff_netcommits_7": -21, "files": 12641, "first_date": "2001-05-02", "last_date": "2015-04-20", "percentage_authors_30": 40, "percentage_authors_365": 0, "percentage_authors_7": 100, "percentage_commits_30": 5, "percentage_commits_365": 8, "percentage_commits_7": 100, "removed_lines": 268249.0, "repositories": 1}