{"added_lines": 43074.0, "authors": 3, "authors_30": 2, "authors_365": 2, "authors_7": 1, "avg_commits_author": 65.33, "avg_commits_month": 10.32, "commits": 196, "commits_30": 8, "commits_365": 88, "commits_7": 4, "committers": 3, "diff_netauthors_30": 2, "diff_netauthors_365": 0, "diff_netauthors_7": 0, "diff_netcommits_30": 8, "diff_netcommits_365": -20, "diff_netcommits_7": 2, "files": 637, "first_date": "2001-05-02", "last_date": "2015-05-05", "percentage_authors_30": 0, "percentage_authors_365": 0, "percentage_authors_7": 0, "percentage_commits_30": 0, "percentage_commits_365": 18, "percentage_commits_7": 100, "removed_lines": 17960.0, "repositories": 1}