{"authors": 34, "authors_30": 15, "authors_365": 26, "authors_7": 2, "avg_commits_author": 225.35, "avg_commits_month": 178.19, "commits": 7662, "commits_30": 302, "commits_365": 2360, "commits_7": 3, "committers": 34, "diff_netauthors_30": 0, "diff_netauthors_365": -1, "diff_netauthors_7": -12, "diff_netcommits_30": 68, "diff_netcommits_365": 522, "diff_netcommits_7": -92, "files": 12337, "first_date": "2012-03-02", "last_date": "2015-10-29", "percentage_authors_30": 0, "percentage_authors_365": 3, "percentage_authors_7": 85, "percentage_commits_30": 29, "percentage_commits_365": 28, "percentage_commits_7": 96, "repositories": 1}