{"authors.": {"authors": ["Greg Watson", "Beth Tibbitts", "Kam Man Chu", "cvs2svn", "Vivian Kong", "Albert L. Rossi", "Chris Recoskie", "John Eblen", "Nathan DeBardeleben", "Claudia Knobloch"], "commits": [5498, 1216, 860, 829, 629, 521, 252, 179, 177, 164], "id": [1489, 2585, 2583, 180, 25, 2592, 2589, 2600, 2582, 2597]}, "authors.last month": {"authors": ["Greg Watson", "John Eblen", "Steven R. Brandt"], "commits": [3, 1, 1], "id": [1489, 2600, 2622]}, "authors.last year": {"authors": ["Greg Watson", "Carsten Karbach", "Beth Tibbitts", "John Eblen", "dwootton", "Chris Navarro", "Steven R. Brandt", "Rui Liu", "Yang Yang", "Wyatt Spear"], "commits": [117, 104, 39, 20, 12, 9, 5, 4, 4, 3], "id": [1489, 2605, 2585, 2600, 2591, 2614, 2622, 2621, 2616, 2587]}}