{"authors": 51, "authors_30": 11, "authors_365": 26, "authors_7": 2, "avg_commits_author": 282.65, "avg_commits_month": 122.16, "commits": 14407, "commits_30": 44, "commits_365": 1129, "commits_7": 5, "committers": 43, "diff_netauthors_30": -2, "diff_netauthors_365": 5, "diff_netauthors_7": -3, "diff_netcommits_30": -83, "diff_netcommits_365": -399, "diff_netcommits_7": 0, "files": 45936, "first_date": "2005-12-05", "last_date": "2015-10-12", "percentage_authors_30": 15, "percentage_authors_365": 23, "percentage_authors_7": 60, "percentage_commits_30": 65, "percentage_commits_365": 26, "percentage_commits_7": 0, "repositories": 99}