{"abandoned": 241, "abandoned_30": 3, "abandoned_365": 93, "abandoned_7": 0, "active_core_reviewers": 28, "active_core_reviewers_30": 9, "active_core_reviewers_365": 18, "active_core_reviewers_7": 3, "closed": 1843, "closed_30": 44, "closed_365": 768, "closed_7": 13, "diff_netabandoned_30": -9, "diff_netabandoned_365": 38, "diff_netabandoned_7": -1, "diff_netactive_core_reviewers_30": 2, "diff_netactive_core_reviewers_365": 0, "diff_netactive_core_reviewers_7": -2, "diff_netclosed_30": 5, "diff_netclosed_365": 124, "diff_netclosed_7": 6, "diff_netmerged_30": 14, "diff_netmerged_365": 86, "diff_netmerged_7": 7, "diff_netparticipants_30": 0, "diff_netparticipants_365": 2, "diff_netparticipants_7": -1, "diff_netpatchset_submitters_30": -5, "diff_netpatchset_submitters_365": 3, "diff_netpatchset_submitters_7": 0, "diff_netpending_30": 2, "diff_netpending_365": 5, "diff_netpending_7": 1, "diff_netreviewers_30": 7, "diff_netreviewers_365": 8, "diff_netreviewers_7": -1, "diff_netsent_patchsets_30": 60, "diff_netsent_patchsets_365": 423, "diff_netsent_patchsets_7": 10, "diff_netsubmitted_30": 7, "diff_netsubmitted_365": 129, "diff_netsubmitted_7": 7, "diff_netsubmitters_30": -6, "diff_netsubmitters_365": 2, "diff_netsubmitters_7": 1, "diff_netvoted_patchsets_30": 30, "diff_netvoted_patchsets_365": 196, "diff_netvoted_patchsets_7": -2, "first_date": "2012-04-22", "inprogress": 0, "last_date": "2016-04-14", "merged": 1602, "merged_30": 41, "merged_365": 675, "merged_7": 13, "new": 68, "opened": 68, "participants": 128, "participants_30": 26, "participants_365": 77, "participants_7": 10, "patchset_submitters": 116, "patchset_submitters_30": 17, "patchset_submitters_365": 69, "patchset_submitters_7": 7, "pending": 68, "pending_30": 11, "pending_365": 38, "pending_7": 2, "percentage_abandoned_30": 75, "percentage_abandoned_365": 69, "percentage_abandoned_7": 100, "percentage_active_core_reviewers_30": 28, "percentage_active_core_reviewers_365": 0, "percentage_active_core_reviewers_7": 40, "percentage_closed_30": 12, "percentage_closed_365": 19, "percentage_closed_7": 85, "percentage_merged_30": 51, "percentage_merged_365": 14, "percentage_merged_7": 116, "percentage_participants_30": 0, "percentage_participants_365": 2, "percentage_participants_7": 9, "percentage_patchset_submitters_30": 22, "percentage_patchset_submitters_365": 4, "percentage_patchset_submitters_7": 0, "percentage_pending_30": 22, "percentage_pending_365": 15, "percentage_pending_7": 100, "percentage_reviewers_30": 77, "percentage_reviewers_365": 27, "percentage_reviewers_7": 16, "percentage_sent_patchsets_30": 41, "percentage_sent_patchsets_365": 19, "percentage_sent_patchsets_7": 28, "percentage_submitted_30": 14, "percentage_submitted_365": 19, "percentage_submitted_7": 87, "percentage_submitters_30": 33, "percentage_submitters_365": 3, "percentage_submitters_7": 25, "percentage_voted_patchsets_30": 63, "percentage_voted_patchsets_365": 17, "percentage_voted_patchsets_7": 11, "review_time_days_avg": 7.43, "review_time_days_median": 0.37, "reviewers": 55, "reviewers_30": 16, "reviewers_365": 37, "reviewers_7": 5, "sent_patchsets": 5984, "sent_patchsets_30": 206, "sent_patchsets_365": 2577, "sent_patchsets_7": 45, "submitted": 1911, "submitted_30": 55, "submitted_365": 806, "submitted_7": 15, "submitters": 117, "submitters_30": 12, "submitters_365": 62, "submitters_7": 5, "voted_patchsets": 2966, "voted_patchsets_30": 77, "voted_patchsets_365": 1313, "voted_patchsets_7": 15}