{"authors.": {"authors": ["Tom Watson", "Pascal Rapicault", "John_Arthorne@ca.ibm.com", "Andrew Niefer", "dj", "Susan McCourt", "Simon Kaegi", "Jeff McAffer", "cvs2svn", ""], "commits": [3991, 1997, 1572, 1283, 1072, 884, 881, 276, 260, 211], "id": [589, 670, 411, 412, 1394, 417, 418, 658, 180, 1959]}, "authors.last month": {"authors": ["Tom Watson", "Pascal Rapicault", "Szymon Ptaszkiewicz", "Raymond Auge", "Arun Thondapu", "Christian Georgi", "Silenio Quarti", "Christian Schneider", "Mikael Barbero", "Mat Booth"], "commits": [24, 12, 10, 9, 6, 4, 4, 3, 2, 1], "id": [589, 670, 258, 3119, 1656, 277, 424, 334, 825, 910]}, "authors.last year": {"authors": ["Tom Watson", "Raymond Auge", "Pascal Rapicault", "Arun Thondapu", "Szymon Ptaszkiewicz", "Tobias Oberlies", "mkeller", "Silenio Quarti", "Alexander Kurtakov", "Sravan Kumar Lakkimsetti"], "commits": [220, 73, 61, 39, 10, 9, 8, 8, 7, 7], "id": [589, 3119, 670, 1656, 258, 1307, 197, 424, 587, 2076]}, "company_commits": [9775, 2152, 1811, 345, 225, 175, 156, 98, 98, 57], "name": ["IBM", "RAPICORP", "individual", "SAP AG", "GoPivotal, Inc.", "EclipseSource (See Innoopract)", "Cloudsmith Inc.", "compeople AG", "Red Hat, Inc.", "Tasktop"]}