{"bmitickets": 90.27, "changed": 1926, "changers": 388, "closed": 1773, "closed_30": 5, "closed_365": 105, "closed_7": 1, "closers": 49, "closers_30": 2, "closers_365": 5, "closers_7": 1, "diff_netclosed_30": 0, "diff_netclosed_365": -168, "diff_netclosed_7": 0, "diff_netclosers_30": 0, "diff_netclosers_365": 0, "diff_netclosers_7": 0, "first_date": "2004-12-03", "last_date": "2015-04-16", "opened": 1964, "openers": 293, "percentage_closed_30": 0, "percentage_closed_365": 61, "percentage_closed_7": 0, "percentage_closers_30": 0, "percentage_closers_365": 0, "percentage_closers_7": 0, "trackers": 1}