{"changed": 11964, "changers": 2945, "closed": 10134, "closed_30": 45, "closed_365": 326, "closed_7": 7, "closers": 371, "closers_30": 10, "closers_365": 41, "closers_7": 3, "diff_netclosed_30": -20, "diff_netclosed_365": -127, "diff_netclosed_7": 0, "diff_netclosers_30": 0, "diff_netclosers_365": 0, "diff_netclosers_7": -1, "opened": 12337, "openers": 2254, "percentage_closed_30": 30, "percentage_closed_365": 28, "percentage_closed_7": 0, "percentage_closers_30": 0, "percentage_closers_365": 0, "percentage_closers_7": 25, "trackers": 1}