{"authors": 50, "authors_30": 4, "authors_365": 21, "authors_7": 1, "avg_commits_author": 110.9, "avg_commits_month": 37.47, "commits": 5545, "commits_30": 20, "commits_365": 211, "commits_7": 1, "committers": 50, "diff_netauthors_30": -4, "diff_netauthors_365": 0, "diff_netauthors_7": 0, "diff_netcommits_30": -8, "diff_netcommits_365": 0, "diff_netcommits_7": -1, "files": 12764, "first_date": "2003-11-25", "last_date": "2016-04-14", "percentage_authors_30": 50, "percentage_authors_365": 0, "percentage_authors_7": 0, "percentage_commits_30": 28, "percentage_commits_365": 0, "percentage_commits_7": 50, "repositories": 2}