{"added_lines": 2303032.0, "authors": 24, "authors_30": 5, "authors_365": 5, "authors_7": 3, "avg_commits_author": 449.08, "avg_commits_month": 153.97, "commits": 10778, "commits_30": 90, "commits_365": 1761, "commits_7": 15, "committers": 24, "diff_netauthors_30": 0, "diff_netauthors_365": -7, "diff_netauthors_7": 0, "diff_netcommits_30": -26, "diff_netcommits_365": -489, "diff_netcommits_7": -3, "files": 14011, "first_date": "2001-05-02", "last_date": "2015-02-01", "percentage_authors_30": 0, "percentage_authors_365": 58, "percentage_authors_7": 0, "percentage_commits_30": 22, "percentage_commits_365": 21, "percentage_commits_7": 16, "removed_lines": 1494467.0, "repositories": 5}