{"authors": 3273, "authors_30": 365, "authors_365": 1087, "authors_7": 112, "avg_commits_author": 325.45, "avg_commits_month": 6130.92, "commits": 999067, "commits_30": 4027, "commits_365": 64454, "commits_7": 416, "committers": 3273, "core": 402, "diff_netauthors_30": -20, "diff_netauthors_365": 10, "diff_netauthors_7": -101, "diff_netcommits_30": -646, "diff_netcommits_365": 1766, "diff_netcommits_7": -645, "files": 5305661, "first_date": "2001-05-02", "last_date": "2015-10-27", "occasional": 2343, "organizations": 173, "percentage_authors_30": 5, "percentage_authors_365": 0, "percentage_authors_7": 47, "percentage_commits_30": 13, "percentage_commits_365": 2, "percentage_commits_7": 60, "regular": 514, "repositories": 539, "type": "git", "url": "http://git.eclipse.org/gitroot/recommenders.incubator/org.eclipse.recommenders.codesearch.git"}