{"added_lines": 626132169.0, "authors": 2900, "authors_30": 351, "authors_365": 1097, "authors_7": 196, "avg_commits_author": 357.12, "avg_commits_month": 6173.63, "commits": 969382, "commits_30": 4553, "commits_365": 63749, "commits_7": 1069, "committers": 2900, "companies": 97, "core": 359, "diff_netauthors_30": -29, "diff_netauthors_365": 68, "diff_netauthors_7": -17, "diff_netcommits_30": -394, "diff_netcommits_365": -514, "diff_netcommits_7": -45, "files": 5260921, "first_date": "2001-05-02", "last_date": "2015-04-27", "occasional": 2151, "percentage_authors_30": 7, "percentage_authors_365": 6, "percentage_authors_7": 7, "percentage_commits_30": 7, "percentage_commits_365": 0, "percentage_commits_7": 4, "regular": 447, "removed_lines": 365848827.0, "repositories": 539, "type": "git", "url": "http://git.eclipse.org/gitroot/koneki/org.eclipse.koneki.ldt.git"}