{"WaitingForReviewer": 56, "WaitingForSubmitter": 81, "abandoned": 3590, "abandoned_30": 86, "abandoned_365": 2052, "abandoned_7": 3, "active_core_reviewers": 273, "active_core_reviewers_30": 101, "active_core_reviewers_365": 228, "active_core_reviewers_7": 32, "approved": 0, "closed": 22343, "closed_30": 826, "closed_365": 14294, "closed_7": 37, "codereview": 39797, "diff_netabandoned_30": -29, "diff_netabandoned_365": 1230, "diff_netabandoned_7": -13, "diff_netactive_core_reviewers_30": -25, "diff_netactive_core_reviewers_365": 76, "diff_netactive_core_reviewers_7": -15, "diff_netclosed_30": -653, "diff_netclosed_365": 9026, "diff_netclosed_7": -121, "diff_netmerged_30": -624, "diff_netmerged_365": 7796, "diff_netmerged_7": -108, "diff_netparticipants_30": -16, "diff_netparticipants_365": 350, "diff_netparticipants_7": -44, "diff_netpending_30": 55, "diff_netpending_365": 560, "diff_netpending_7": -50, "diff_netsubmitted_30": -598, "diff_netsubmitted_365": 9586, "diff_netsubmitted_7": -171, "diff_netsubmitters_30": -10, "diff_netsubmitters_365": 260, "diff_netsubmitters_7": -37, "first_date": "2012-02-24", "inprogress": 0, "last_date": "2015-07-01", "merged": 18753, "merged_30": 740, "merged_365": 12242, "merged_7": 34, "new": 1305, "opened": 1305, "companies": 93, "participants": 966, "participants_30": 261, "participants_365": 926, "participants_7": 95, "pending": 1302, "pending_30": 312, "pending_365": 1096, "pending_7": 66, "percentage_abandoned_30": 25, "percentage_abandoned_365": 149, "percentage_abandoned_7": 81, "percentage_active_core_reviewers_30": 19, "percentage_active_core_reviewers_365": 50, "percentage_active_core_reviewers_7": 31, "percentage_closed_30": 44, "percentage_closed_365": 171, "percentage_closed_7": 76, "percentage_merged_30": 45, "percentage_merged_365": 175, "percentage_merged_7": 76, "percentage_participants_30": 5, "percentage_participants_365": 60, "percentage_participants_7": 31, "percentage_pending_30": 21, "percentage_pending_365": 104, "percentage_pending_7": 43, "percentage_submitted_30": 34, "percentage_submitted_365": 165, "percentage_submitted_7": 62, "percentage_submitters_30": 4, "percentage_submitters_365": 64, "percentage_submitters_7": 38, "repositories": 166, "review_time_days_avg": 21.18, "review_time_days_median": 1.12, "reviewers": 958, "sent": 22295, "submitted": 23645, "submitted_30": 1138, "submitted_365": 15390, "submitted_7": 103, "submitters": 884, "submitters_30": 206, "submitters_365": 666, "submitters_7": 58, "verified": 52595}