{"WaitingForReviewer": 95, "WaitingForSubmitter": 119, "abandoned": 4656, "abandoned_30": 108, "abandoned_365": 2287, "abandoned_7": 0, "active_core_reviewers": 306, "active_core_reviewers_30": 111, "active_core_reviewers_365": 239, "active_core_reviewers_7": 2, "approved": 0, "closed": 29503, "closed_30": 774, "closed_365": 16840, "closed_7": 1, "codereview": 55316, "diff_netabandoned_30": -26, "diff_netabandoned_365": 1068, "diff_netabandoned_7": -11, "diff_netactive_core_reviewers_30": -6, "diff_netactive_core_reviewers_365": 47, "diff_netactive_core_reviewers_7": -32, "diff_netclosed_30": -338, "diff_netclosed_365": 8914, "diff_netclosed_7": -39, "diff_netmerged_30": -312, "diff_netmerged_365": 7846, "diff_netmerged_7": -28, "diff_netparticipants_30": -37, "diff_netparticipants_365": -52, "diff_netparticipants_7": -88, "diff_netpending_30": -161, "diff_netpending_365": 435, "diff_netpending_7": -35, "diff_netsubmitted_30": -499, "diff_netsubmitted_365": 9349, "diff_netsubmitted_7": -74, "diff_netsubmitters_30": -46, "diff_netsubmitters_365": 141, "diff_netsubmitters_7": -38, "first_date": "2012-02-24", "inprogress": 0, "last_date": "2015-12-08", "merged": 24847, "merged_30": 666, "merged_365": 14553, "merged_7": 1, "new": 1548, "opened": 1548, "companies": 99, "participants": 1109, "participants_30": 251, "participants_365": 902, "participants_7": 4, "pending": 1546, "pending_30": 223, "pending_365": 1233, "pending_7": 0, "percentage_abandoned_30": 19, "percentage_abandoned_365": 87, "percentage_abandoned_7": 100, "percentage_active_core_reviewers_30": 5, "percentage_active_core_reviewers_365": 24, "percentage_active_core_reviewers_7": 94, "percentage_closed_30": 30, "percentage_closed_365": 112, "percentage_closed_7": 97, "percentage_merged_30": 31, "percentage_merged_365": 116, "percentage_merged_7": 96, "percentage_participants_30": 12, "percentage_participants_365": 5, "percentage_participants_7": 95, "percentage_pending_30": 41, "percentage_pending_365": 54, "percentage_pending_7": 100, "percentage_submitted_30": 33, "percentage_submitted_365": 107, "percentage_submitted_7": 98, "percentage_submitters_30": 21, "percentage_submitters_365": 26, "percentage_submitters_7": 97, "repositories": 176, "review_time_days_avg": 19.04, "review_time_days_median": 1.13, "reviewers": 1110, "sent": 30348, "submitted": 31049, "submitted_30": 997, "submitted_365": 18073, "submitted_7": 1, "submitters": 1024, "submitters_30": 171, "submitters_365": 673, "submitters_7": 1, "verified": 70541}