{"added_lines": 7394945.0, "authors": 15, "authors_30": 6, "authors_365": 9, "authors_7": 3, "avg_commits_author": 1897.13, "avg_commits_month": 196.26, "commits": 28457, "commits_30": 67, "commits_365": 744, "commits_7": 15, "committers": 14, "diff_netauthors_30": 1, "diff_netauthors_365": -1, "diff_netauthors_7": -1, "diff_netcommits_30": 34, "diff_netcommits_365": -682, "diff_netcommits_7": 0, "files": 53359, "first_date": "2001-05-02", "last_date": "2015-02-01", "percentage_authors_30": 20, "percentage_authors_365": 9, "percentage_authors_7": 25, "percentage_commits_30": 103, "percentage_commits_365": 47, "percentage_commits_7": 0, "removed_lines": 3364454.0, "repositories": 48}