{"authors": 121, "authors_30": 4, "authors_365": 42, "authors_7": 1, "avg_commits_author": 36.35, "avg_commits_month": 59.75, "commits": 4362, "commits_30": 13, "commits_365": 449, "commits_7": 2, "committers": 121, "diff_netauthors_30": -8, "diff_netauthors_365": 9, "diff_netauthors_7": 0, "diff_netcommits_30": -54, "diff_netcommits_365": 17, "diff_netcommits_7": 0, "files": 3336, "first_date": "2009-09-23", "last_date": "2015-10-28", "percentage_authors_30": 66, "percentage_authors_365": 27, "percentage_authors_7": 0, "percentage_commits_30": 80, "percentage_commits_365": 3, "percentage_commits_7": 0, "repositories": 3}