{"added_lines": 1012583.0, "authors": 7, "authors_30": 5, "authors_365": 9, "authors_7": 2, "avg_commits_author": 59.29, "avg_commits_month": 59.29, "commits": 415, "commits_30": 32, "commits_365": 424, "commits_7": 11, "committers": 7, "diff_netauthors_30": -2, "diff_netauthors_365": 9, "diff_netauthors_7": 0, "diff_netcommits_30": -38, "diff_netcommits_365": 424, "diff_netcommits_7": 7, "files": 9236, "first_date": "2001-05-02", "last_date": "2015-01-16", "percentage_authors_30": 28, "percentage_authors_365": 0, "percentage_authors_7": 0, "percentage_commits_30": 54, "percentage_commits_365": 0, "percentage_commits_7": 175, "removed_lines": 75487.0, "repositories": 1}