{"authors.": {"authors": ["Greg Watson", "Jeffrey Overbey", "Beth Tibbitts", "cvs2svn", "Kam Man Chu", "Vivian Kong", "Albert L. Rossi", "Chris Recoskie", "John Eblen", "Carsten Karbach"], "commits": [6000, 1334, 1247, 894, 860, 643, 521, 252, 207, 197], "id": [1489, 1483, 2585, 180, 2583, 25, 2592, 2589, 2600, 2605]}, "authors.last month": {"authors": ["Greg Watson", "Doug Schaefer", "John Eblen", "Marc-Andre Laperle", "Matthew Bastien"], "commits": [12, 2, 1, 1, 1], "id": [1489, 24, 2600, 540, 457842]}, "authors.last year": {"authors": ["Greg Watson", "Jeffrey Overbey", "Beth Tibbitts", "John Eblen", "Roland Schulz", "Steven R. Brandt", "Chris Navarro", "Marc-Andre Laperle", "Doug Schaefer", "Bernd Hufmann"], "commits": [190, 33, 30, 21, 12, 8, 6, 5, 4, 3], "id": [1489, 1483, 2585, 2600, 2510, 2622, 2614, 540, 24, 2441]}, "company_commits": [7302, 5635, 11, 8, 4, 4, 1], "name": ["IBM", "individual", "Ericsson AB", "Intel Corporation", "Blackberry Limited", "Red Hat, Inc.", "QNX Software Systems Co."]}