{"authors": 40, "authors_30": 7, "authors_365": 16, "authors_7": 1, "avg_commits_author": 409.63, "avg_commits_month": 105.71, "commits": 16385, "commits_30": 30, "commits_365": 851, "commits_7": 2, "committers": 24, "diff_netauthors_30": 0, "diff_netauthors_365": 0, "diff_netauthors_7": -2, "diff_netcommits_30": -18, "diff_netcommits_365": -449, "diff_netcommits_7": -2, "files": 31355, "first_date": "2002-10-01", "last_date": "2015-09-28", "percentage_authors_30": 0, "percentage_authors_365": 0, "percentage_authors_7": 66, "percentage_commits_30": 37, "percentage_commits_365": 34, "percentage_commits_7": 50, "repositories": 20}