{"added_lines": 582296.0, "authors": 4, "authors_30": 1, "authors_365": 2, "authors_7": 1, "avg_commits_author": 775.5, "avg_commits_month": 38.77, "commits": 3102, "commits_30": 30, "commits_365": 369, "commits_7": 11, "committers": 4, "diff_netauthors_30": 0, "diff_netauthors_365": 0, "diff_netauthors_7": 0, "diff_netcommits_30": -5, "diff_netcommits_365": -49, "diff_netcommits_7": 5, "files": 1482, "first_date": "2001-05-02", "last_date": "2014-10-20", "percentage_authors_30": 0, "percentage_authors_365": 0, "percentage_authors_7": 0, "percentage_commits_30": 14, "percentage_commits_365": 11, "percentage_commits_7": 83, "removed_lines": 422017.0, "repositories": 5}