{"changed": 18826, "changers": 37, "closed": 6196, "closed_30": 15, "closed_365": 350, "closed_7": 6, "closers": 29, "closers_30": 3, "closers_365": 3, "closers_7": 2, "diff_netclosed_30": -15, "diff_netclosed_365": 220, "diff_netclosed_7": 2, "diff_netclosers_30": 0, "diff_netclosers_365": -4, "diff_netclosers_7": 0, "opened": 3450, "openers": 36, "percentage_closed_30": 50, "percentage_closed_365": 169, "percentage_closed_7": 50, "percentage_closers_30": 0, "percentage_closers_365": 57, "percentage_closers_7": 0, "trackers": 53}